easyqueue/__init__.py
easyqueue/client/__init__.py
easyqueue/client/base_client.py
easyqueue/client/eqobject_client.py
easyqueue/core/__init__.py
easyqueue/core/base/__init__.py
easyqueue/core/base/eqobject.py
easyqueue/core/base/test_eqobject.py
easyqueue/core/objects/__init__.py
easyqueue/core/objects/base/__init__.py
easyqueue/core/objects/base/eqobject.py
easyqueue/core/objects/base/schema.py
easyqueue/core/objects/queue/__init__.py
easyqueue/core/objects/queue/queue.py
easyqueue/core/objects/queue/schema.py
easyqueue/core/objects/rest/__init__.py
easyqueue/core/objects/rest/restservice.py
easyqueue/core/objects/rest/schema.py
easyqueue/core/objects/ticket/__init__.py
easyqueue/core/objects/ticket/schema.py
easyqueue/core/objects/ticket/ticket.py
easyqueue/core/objects/user/__init__.py
easyqueue/core/objects/user/schema.py
easyqueue/core/objects/user/user.py
easyqueue/core/response/__init__.py
easyqueue/core/response/http_response.py
easyqueue/core/response/response.py
easyqueue/core/response/response_code.py
easyqueue/database/__init__.py
easyqueue/database/mongo/__init__.py
easyqueue/database/mongo/exception_mapper.py
easyqueue/database/mongo/repository.py
easyqueue/database/mongo/utils.py
easyqueue/enums/RestHeaders.py
easyqueue/enums/RestMethods.py
easyqueue/enums/RestProtocols.py
easyqueue/enums/__init__.py
easyqueue/service/__init__.py
easyqueue/service/base_crud_service.py
easyqueue/service/base_ie_service.py
easyqueue/service/mongo_crud_service.py
easyqueue/service/mongo_ie_service.py
easyqueue/utils/__init__.py
easyqueue/utils/validation.py
easyqueue_core-0.0.1.dist-info/LICENSE
easyqueue_core-0.0.1.dist-info/METADATA
easyqueue_core-0.0.1.dist-info/WHEEL
easyqueue_core-0.0.1.dist-info/top_level.txt
easyqueue_core-0.0.1.dist-info/RECORD
